trellobug/__init__.py
trellobug/trellobug.py
trellobug-1.1.1.dist-info/DESCRIPTION.rst
trellobug-1.1.1.dist-info/METADATA
trellobug-1.1.1.dist-info/RECORD
trellobug-1.1.1.dist-info/WHEEL
trellobug-1.1.1.dist-info/entry_points.txt
trellobug-1.1.1.dist-info/metadata.json
trellobug-1.1.1.dist-info/top_level.txt
