Metadata-Version: 2.0
Name: trellobug
Version: 1.1.1
Summary: Files Bugzilla bugs from Trello cards
Home-page: https://github.com/markrcote/trellobug/
Author: Mark Côté
Author-email: mark.cote@uwaterloo.ca
License: MPL 2.0
Keywords: trello bugzilla
Platform: UNKNOWN
Classifier: Development Status :: 4 - Beta
Classifier: Environment :: Console
Classifier: Intended Audience :: Developers
Classifier: License :: OSI Approved :: Mozilla Public License 2.0 (MPL 2.0)
Classifier: Programming Language :: Python :: 3
Classifier: Programming Language :: Python :: 3.5
Classifier: Programming Language :: Python :: 3.6
Classifier: Topic :: Software Development
Requires-Dist: oauthlib (==2.0.1)
Requires-Dist: py-trello (==0.9.0)
Requires-Dist: python-dateutil (==2.6.0)
Requires-Dist: pytz (==2016.10)
Requires-Dist: requests (==2.13.0)
Requires-Dist: requests-oauthlib (==0.8.0)
Requires-Dist: six (==1.10.0)
